fastcrawl/__init__.py
fastcrawl/cli.py
fastcrawl/py.typed
fastcrawl/types_.py
fastcrawl/core/__init__.py
fastcrawl/core/app.py
fastcrawl/core/crawler.py
fastcrawl/core/http_client.py
fastcrawl/core/components/__init__.py
fastcrawl/core/components/dependencies.py
fastcrawl/core/components/func_wrapper.py
fastcrawl/core/components/handler.py
fastcrawl/core/components/pipeline.py
fastcrawl/core/components/startup.py
fastcrawl/core/components/validation.py
fastcrawl/models/__init__.py
fastcrawl/models/app_settings.py
fastcrawl/models/http_settings.py
fastcrawl/models/logging_settings.py
fastcrawl/models/request.py
fastcrawl/models/response.py
fastcrawl-1.1.0.dist-info/licenses/LICENSE
fastcrawl-1.1.0.dist-info/METADATA
fastcrawl-1.1.0.dist-info/WHEEL
fastcrawl-1.1.0.dist-info/top_level.txt
fastcrawl-1.1.0.dist-info/RECORD
