Metadata-Version: 2.4
Name: fastcrawl
Version: 1.1.0
Summary: Fast and asynchronous web crawling and scraping library for Python.
Author-email: ilarionkuleshov <ilarion.kuleshov@gmail.com>
License-Expression: MIT
Requires-Python: <3.14,>=3.9
License-File: LICENSE
Requires-Dist: httpx>=0.28.1
Requires-Dist: parsel>=1.10.0
Requires-Dist: pydantic>=2.11.4
Requires-Dist: pydantic-settings>=2.9.1
Requires-Dist: typeguard>=4.4.4
Requires-Dist: typer>=0.15.3
Dynamic: license-file
